Renewable_Suitability_Predictor/Interface.py
Renewable_Suitability_Predictor/__init__.py
Renewable_Suitability_Predictor/backend_methods.py
Renewable_Suitability_Predictor/solar_dataset.csv
Renewable_Suitability_Predictor/wind_dataset.csv
Renewable_Suitability_Predictor-0.2.0.dist-info/LICENSE.txt
Renewable_Suitability_Predictor-0.2.0.dist-info/METADATA
Renewable_Suitability_Predictor-0.2.0.dist-info/WHEEL
Renewable_Suitability_Predictor-0.2.0.dist-info/top_level.txt
Renewable_Suitability_Predictor-0.2.0.dist-info/RECORD
